elastic_site_search/__init__.py
elastic_site_search/client.py
elastic_site_search/version.py
elastic_site_search-2.1.1.dist-info/LICENSE
elastic_site_search-2.1.1.dist-info/METADATA
elastic_site_search-2.1.1.dist-info/NOTICE.txt
elastic_site_search-2.1.1.dist-info/WHEEL
elastic_site_search-2.1.1.dist-info/top_level.txt
elastic_site_search-2.1.1.dist-info/RECORD
